easykey/__init__.py
easykey-0.1.0.dist-info/licenses/LICENSE
easykey-0.1.0.dist-info/METADATA
easykey-0.1.0.dist-info/WHEEL
easykey-0.1.0.dist-info/top_level.txt
easykey-0.1.0.dist-info/RECORD
